apgard/__init__.py
apgard/breaks.py
apgard/client.py
apgard/enums.py
apgard/errors.py
apgard/moderation.py
apgard/async_client/__init__.py
apgard/async_client/async_breaks.py
apgard/async_client/async_client.py
apgard/async_client/async_moderation.py
apgard-0.1.8.dist-info/METADATA
apgard-0.1.8.dist-info/WHEEL
apgard-0.1.8.dist-info/top_level.txt
apgard-0.1.8.dist-info/RECORD
