Metadata-Version: 2.4
Name: apgard
Version: 0.1.8
Summary: SDK for safeguarding AI chatbots and minors
Home-page: https://github.com/ariel-colon/apgard.git
Author: Ariel Colon
Author-email: ariel@apgardai.com
Classifier: Programming Language :: Python :: 3
Classifier: License :: OSI Approved :: MIT License
Classifier: Operating System :: OS Independent
Requires-Python: >=3.7
Requires-Dist: requests>=2.25.0
Requires-Dist: python-dotenv>=0.19.0
Requires-Dist: nest_asyncio>=1.6.0
Requires-Dist: httpx>=0.28.1
Dynamic: author
Dynamic: author-email
Dynamic: classifier
Dynamic: description
Dynamic: description-content-type
Dynamic: home-page
Dynamic: requires-dist
Dynamic: requires-python
Dynamic: summary
